smdpy/__init__.py
smdpy/social/__init__.py
smdpy/social/instagram.py
smdpy/social/youtube.py
smdpy-1.0.1.dist-info/LICENSE
smdpy-1.0.1.dist-info/METADATA
smdpy-1.0.1.dist-info/WHEEL
smdpy-1.0.1.dist-info/top_level.txt
smdpy-1.0.1.dist-info/RECORD
